openedx_cmi5_xblock/__init__.py
openedx_cmi5_xblock/openedx_cmi5_xblock.py
openedx_cmi5_xblock/locale/__init__.py
openedx_cmi5_xblock/locale/settings.py
openedx_cmi5_xblock/static/README.txt
openedx_cmi5_xblock/static/css/openedx_cmi5_xblock.css
openedx_cmi5_xblock/static/html/openedx_cmi5_xblock.html
openedx_cmi5_xblock/static/html/studio.html
openedx_cmi5_xblock/static/js/src/openedx_cmi5_xblock.js
openedx_cmi5_xblock/static/js/src/studio.js
openedx_cmi5_xblock/translations/__init__.py
openedx_cmi5_xblock/translations/settings.py
openedx_cmi5_xblock/utils/__init__.py
openedx_cmi5_xblock/utils/utility.py
openedx_cmi5_xblock-0.1.3.dist-info/LICENSE
openedx_cmi5_xblock-0.1.3.dist-info/METADATA
openedx_cmi5_xblock-0.1.3.dist-info/WHEEL
openedx_cmi5_xblock-0.1.3.dist-info/entry_points.txt
openedx_cmi5_xblock-0.1.3.dist-info/top_level.txt
openedx_cmi5_xblock-0.1.3.dist-info/RECORD
