Metadata-Version: 2.2
Name: openedx-cmi5-xblock
Version: 0.1.3
Summary: Openedx CMI5 XBlock
Home-page: https://github.com/edly-io/openedx-cmi5-xblock
Author: edly
Author-email: hello@edly.io
License: MIT
Keywords: Python edx cmi5 xblock
Classifier: Development Status :: 3 - Alpha
Classifier: Intended Audience :: Developers
Classifier: License :: OSI Approved :: MIT License
Classifier: Natural Language :: English
Classifier: Programming Language :: Python :: 3
Classifier: Programming Language :: Python :: 3.12
Requires-Python: >=3.8
License-File: LICENSE
Requires-Dist: Mako
Requires-Dist: XBlock
Requires-Dist: django-statici18n
Requires-Dist: edx-i18n-tools
Dynamic: author
Dynamic: author-email
Dynamic: classifier
Dynamic: description
Dynamic: home-page
Dynamic: keywords
Dynamic: license
Dynamic: requires-dist
Dynamic: requires-python
Dynamic: summary
